api/__init__.py
api/app_settings.py
api/asgi.py
api/models.py
api/settings.py
api/urls.py
api/utils.py
api/views.py
api/wsgi.py
tum_common_x-0.1.2.dist-info/licenses/LICENCE
tum_common_x-0.1.2.dist-info/METADATA
tum_common_x-0.1.2.dist-info/WHEEL
tum_common_x-0.1.2.dist-info/entry_points.txt
tum_common_x-0.1.2.dist-info/top_level.txt
tum_common_x-0.1.2.dist-info/RECORD
